{
  "$schema": "https://developer.microsoft.com/json-schemas/fabric/item/report/definition/visualContainer/2.10.0/schema.json",
  "name": "b3000000000000000003",
  "position": {
    "x": 24,
    "y": 32,
    "z": 1002,
    "height": 32,
    "width": 184,
    "tabOrder": 3
  },
  "visual": {
    "visualType": "textbox",
    "objects": {
      "general": [
        {
          "properties": {
            "paragraphs": [
              {
                "textRuns": [
                  {
                    "value": "Filters",
                    "textStyle": {
                      "fontWeight": "bold",
                      "fontSize": "13pt"
                    }
                  }
                ]
              }
            ]
          }
        }
      ]
    },
    "drillFilterOtherVisuals": true
  }
}